kompas_3d_wrapper/__init__.py
kompas_3d_wrapper/__main__.py
kompas_3d_wrapper/py.typed
kompas_3d_wrapper-2023.4.3.dist-info/entry_points.txt
kompas_3d_wrapper-2023.4.3.dist-info/LICENSE
kompas_3d_wrapper-2023.4.3.dist-info/METADATA
kompas_3d_wrapper-2023.4.3.dist-info/WHEEL
kompas_3d_wrapper-2023.4.3.dist-info/RECORD
