Metadata-Version: 2.1
Name: kompas-3d-wrapper
Version: 2023.4.3
Summary: Kompas 3D Wrapper
Home-page: https://github.com/nikolai-in/kompas-3d-wrapper
License: MIT
Author: Nick
Author-email: nikolai.in@tuta.io
Requires-Python: >=3.11,<4.0
Classifier: Development Status :: 3 - Alpha
Classifier: License :: OSI Approved :: MIT License
Classifier: Programming Language :: Python :: 3
Classifier: Programming Language :: Python :: 3.11
Requires-Dist: click (>=8.0.1)
Requires-Dist: psutil (>=5.9.4,<6.0.0)
Requires-Dist: pywin32 (>=305,<306)
Project-URL: Changelog, https://github.com/nikolai-in/kompas-3d-wrapper/releases
Project-URL: Documentation, https://kompas-3d-wrapper.readthedocs.io
Project-URL: Repository, https://github.com/nikolai-in/kompas-3d-wrapper
